pytest_httpx/__init__.py
pytest_httpx/_httpx_internals.py
pytest_httpx/_httpx_mock.py
pytest_httpx/_options.py
pytest_httpx/_pretty_print.py
pytest_httpx/_request_matcher.py
pytest_httpx/py.typed
pytest_httpx/version.py
pytest_httpx-0.34.0.dist-info/LICENSE
pytest_httpx-0.34.0.dist-info/METADATA
pytest_httpx-0.34.0.dist-info/WHEEL
pytest_httpx-0.34.0.dist-info/entry_points.txt
pytest_httpx-0.34.0.dist-info/top_level.txt
pytest_httpx-0.34.0.dist-info/RECORD
