Metadata-Version: 2.1
Name: pytest-httpx
Version: 0.34.0
Summary: Send responses to httpx.
Author-email: Colin Bounouar <colin.bounouar.dev@gmail.com>
Maintainer-email: Colin Bounouar <colin.bounouar.dev@gmail.com>
License: MIT License
Project-URL: documentation, https://colin-b.github.io/pytest_httpx/
Project-URL: repository, https://github.com/Colin-b/pytest_httpx
Project-URL: changelog, https://github.com/Colin-b/pytest_httpx/blob/master/CHANGELOG.md
Project-URL: issues, https://github.com/Colin-b/pytest_httpx/issues
Keywords: httpx,pytest,testing
Classifier: Development Status :: 5 - Production/Stable
Classifier: Framework :: Pytest
Classifier: Intended Audience :: Developers
Classifier: License :: OSI Approved :: MIT License
Classifier: Natural Language :: English
Classifier: Programming Language :: Python
Classifier: Programming Language :: Python :: 3
Classifier: Programming Language :: Python :: 3.9
Classifier: Programming Language :: Python :: 3.10
Classifier: Programming Language :: Python :: 3.11
Classifier: Programming Language :: Python :: 3.12
Classifier: Programming Language :: Python :: 3.13
Classifier: Topic :: Internet :: WWW/HTTP
Classifier: Topic :: Software Development :: Build Tools
Classifier: Typing :: Typed
Requires-Python: >=3.9
License-File: LICENSE
Requires-Dist: httpx==0.27.*
Requires-Dist: pytest==8.*
Provides-Extra: testing
Requires-Dist: pytest-cov==5.*; extra == "testing"
Requires-Dist: pytest-asyncio==0.24.*; extra == "testing"
